exoedge_fileio/__init__.py
exoedge_fileio/__version__.py
exoedge_fileio/fileio.py
exoedge_fileio-20.8.3.dist-info/LICENSE
exoedge_fileio-20.8.3.dist-info/METADATA
exoedge_fileio-20.8.3.dist-info/WHEEL
exoedge_fileio-20.8.3.dist-info/top_level.txt
exoedge_fileio-20.8.3.dist-info/RECORD
