Metadata-Version: 2.1
Name: exoedge-fileio
Version: 20.8.3
Summary: An ExoEdge source for reading and writing files.
Home-page: https://github.com/exosite/lib_exoedge_file_io_python
Author: Exosite LLC
Author-email: support@exosite.com
License: Apache 2.0
Keywords: murano exosite iot iiot client gateway fileio
Platform: UNKNOWN
Classifier: Development Status :: 4 - Beta
Classifier: Programming Language :: Python :: 2.7
Classifier: Programming Language :: Python :: 3.4
Classifier: Programming Language :: Python :: 3.5
Classifier: Programming Language :: Python :: 3.6
Classifier: Operating System :: POSIX :: Linux
Classifier: Topic :: System :: Operating System Kernels :: Linux
Classifier: Topic :: Software Development :: Embedded Systems
Classifier: License :: OSI Approved :: Apache Software License
Requires-Python: <4,>=2.7.9
Requires-Dist: exoedge
